planqk/service/__init__.py
planqk/service/_version.py
planqk/service/auth.py
planqk/service/client.py
planqk/service/datapool.py
planqk/service/sdk/__init__.py
planqk/service/sdk/client.py
planqk/service/sdk/environment.py
planqk/service/sdk/core/__init__.py
planqk/service/sdk/core/api_error.py
planqk/service/sdk/core/client_wrapper.py
planqk/service/sdk/core/datetime_utils.py
planqk/service/sdk/core/file.py
planqk/service/sdk/core/force_multipart.py
planqk/service/sdk/core/http_client.py
planqk/service/sdk/core/http_response.py
planqk/service/sdk/core/jsonable_encoder.py
planqk/service/sdk/core/pydantic_utilities.py
planqk/service/sdk/core/query_encoder.py
planqk/service/sdk/core/remove_none_from_dict.py
planqk/service/sdk/core/request_options.py
planqk/service/sdk/core/serialization.py
planqk/service/sdk/core/unchecked_base_model.py
planqk/service/sdk/core/http_sse/__init__.py
planqk/service/sdk/core/http_sse/_api.py
planqk/service/sdk/core/http_sse/_decoders.py
planqk/service/sdk/core/http_sse/_exceptions.py
planqk/service/sdk/core/http_sse/_models.py
planqk/service/sdk/service_api/__init__.py
planqk/service/sdk/service_api/client.py
planqk/service/sdk/service_api/raw_client.py
planqk/service/sdk/types/__init__.py
planqk/service/sdk/types/hal_link.py
planqk/service/sdk/types/log_entry.py
planqk/service/sdk/types/log_entry_severity.py
planqk/service/sdk/types/request_body.py
planqk/service/sdk/types/result_response.py
planqk/service/sdk/types/result_response_embedded.py
planqk/service/sdk/types/result_response_links.py
planqk/service/sdk/types/service_execution.py
planqk/service/sdk/types/service_execution_status.py
planqk_service_sdk-2.8.0.dist-info/licenses/LICENSE
planqk_service_sdk-2.8.0.dist-info/METADATA
planqk_service_sdk-2.8.0.dist-info/WHEEL
planqk_service_sdk-2.8.0.dist-info/top_level.txt
planqk_service_sdk-2.8.0.dist-info/RECORD
