Metadata-Version: 2.4
Name: planqk-service-sdk
Version: 2.8.0
Summary: SDK to interact with PLANQK Managed Services.
Author-email: Kipu Quantum GmbH <info@kipu-quantum.com>
Maintainer-email: Michael Wurster <michael.wurster@kipu-quantum.com>
License:                                  Apache License
Project-URL: Homepage, https://kipu-quantum.com/platform
Project-URL: Documentation, https://docs.planqk.de
Project-URL: Repository, https://gitlab.com/planqk-foss/planqk-service-sdk
Project-URL: Issues, https://gitlab.com/planqk-foss/planqk-service-sdk/-/issues
Project-URL: Changelog, https://gitlab.com/planqk-foss/planqk-service-sdk/-/releases
Classifier: Programming Language :: Python :: 3
Classifier: License :: OSI Approved :: Apache Software License
Classifier: Operating System :: OS Independent
Requires-Python: >=3.9
License-File: LICENSE
Requires-Dist: authlib>=1.5.1
Requires-Dist: httpx>=0.28.1
Requires-Dist: pydantic<2.10,>=2.5.0
Dynamic: license-file
